<?xml version="1.0" encoding="windows-1252"?>
<XMI xmi.version="1.1" xmlns:UML="omg.org/UML1.3">
	<XMI.header><XMI.documentation><XMI.exporter>Enterprise Architect</XMI.exporter><XMI.exporterVersion>2.5</XMI.exporterVersion></XMI.documentation></XMI.header><XMI.content><UML:Model name="EA Model" xmi.id="MX_EAID_375FD0CA_EC14_4748_A11E_500A8765E17C"><UML:Namespace.ownedElement><UML:Class name="EARootClass" xmi.id="EAID_11111111_5487_4080_A7F4_41526CB0AA00" isRoot="true" isLeaf="false" isAbstract="false"/><UML:Package name="Rules" xmi.id="EAPK_375FD0CA_EC14_4748_A11E_500A8765E17C" isRoot="false" isLeaf="false" isAbstract="false" visibility="public"><UML:ModelElement.taggedValue><UML:TaggedValue tag="parent" value="EAPK_722A55B4_DE1E_4655_97F9_9F9476BB122A"/><UML:TaggedValue tag="created" value="2009-03-31 00:00:00"/><UML:TaggedValue tag="modified" value="2012-03-14 21:51:05"/><UML:TaggedValue tag="iscontrolled" value="TRUE"/><UML:TaggedValue tag="xmlpath" value="ea5\500A8765E17C.xml"/><UML:TaggedValue tag="lastloaddate" value="2014-02-24 20:40:17"/><UML:TaggedValue tag="lastsavedate" value="2014-02-24 20:40:17"/><UML:TaggedValue tag="version" value="2.0"/><UML:TaggedValue tag="isprotected" value="FALSE"/><UML:TaggedValue tag="usedtd" value="FALSE"/><UML:TaggedValue tag="logxml" value="FALSE"/><UML:TaggedValue tag="tpos" value="3"/><UML:TaggedValue tag="packageFlags" value="VCCFG=cosaq-sandbox;CRC=0;"/><UML:TaggedValue tag="batchsave" value="0"/><UML:TaggedValue tag="batchload" value="0"/><UML:TaggedValue tag="phase" value="1.0"/><UML:TaggedValue tag="status" value="Implemented"/><UML:TaggedValue tag="author" value="Johan Wretö"/><UML:TaggedValue tag="complexity" value="1"/><UML:TaggedValue tag="ea_stype" value="Public"/><UML:TaggedValue tag="tpos" value="3"/><UML:TaggedValue tag="gentype" value="Java"/></UML:ModelElement.taggedValue><UML:Namespace.ownedElement><UML:Comment name="Text" xmi.id="EAID_03033933_69CD_487d_9F51_8B10753069F4" visibility="public" namespace="EAPK_375FD0CA_EC14_4748_A11E_500A8765E17C"><UML:ModelElement.taggedValue><UML:TaggedValue tag="documentation" value="These are example models and you might need more and feel free to add more models of your preferences."/><UML:TaggedValue tag="isSpecification" value="false"/><UML:TaggedValue tag="ea_stype" value="Text"/><UML:TaggedValue tag="ea_ntype" value="0"/><UML:TaggedValue tag="version" value="2.0"/><UML:TaggedValue tag="isActive" value="false"/><UML:TaggedValue tag="package" value="EAPK_375FD0CA_EC14_4748_A11E_500A8765E17C"/><UML:TaggedValue tag="date_created" value="2010-06-23 11:54:14"/><UML:TaggedValue tag="date_modified" value="2012-03-14 21:51:05"/><UML:TaggedValue tag="gentype" value="&lt;none&gt;"/><UML:TaggedValue tag="tagged" value="0"/><UML:TaggedValue tag="package_name" value="Rules"/><UML:TaggedValue tag="phase" value="1.0"/><UML:TaggedValue tag="author" value="Johan Wretö"/><UML:TaggedValue tag="complexity" value="1"/><UML:TaggedValue tag="status" value="Implemented"/><UML:TaggedValue tag="tpos" value="0"/><UML:TaggedValue tag="ea_localid" value="57"/><UML:TaggedValue tag="ea_eleType" value="element"/><UML:TaggedValue tag="style" value="BackColor=-1;BorderColor=-1;BorderWidth=-1;FontColor=-1;VSwimLanes=1;HSwimLanes=1;BorderStyle=0;"/></UML:ModelElement.taggedValue></UML:Comment><UML:Collaboration xmi.id="EAID_375FD0CA_EC14_4748_A11E_500A8765E17C_Collaboration" name="Collaborations"><UML:Namespace.ownedElement><UML:ClassifierRole name="Business rules" xmi.id="EAID_0DB4257C_0307_491f_8099_460B82488F86" visibility="public" base="EAID_11111111_5487_4080_A7F4_41526CB0AA00"><UML:ModelElement.taggedValue><UML:TaggedValue tag="isAbstract" value="false"/><UML:TaggedValue tag="isSpecification" value="false"/><UML:TaggedValue tag="ea_stype" value="Package"/><UML:TaggedValue tag="ea_ntype" value="0"/><UML:TaggedValue tag="version" value="2.0"/><UML:TaggedValue tag="isActive" value="false"/><UML:TaggedValue tag="package" value="EAPK_375FD0CA_EC14_4748_A11E_500A8765E17C"/><UML:TaggedValue tag="date_created" value="2009-04-16 14:21:27"/><UML:TaggedValue tag="date_modified" value="2012-03-14 21:51:05"/><UML:TaggedValue tag="gentype" value="Java"/><UML:TaggedValue tag="tagged" value="0"/><UML:TaggedValue tag="package2" value="EAID_0DB4257C_0307_491f_8099_460B82488F86"/><UML:TaggedValue tag="package_name" value="Rules"/><UML:TaggedValue tag="phase" value="1.0"/><UML:TaggedValue tag="author" value="Johan Wretö"/><UML:TaggedValue tag="complexity" value="1"/><UML:TaggedValue tag="status" value="Implemented"/><UML:TaggedValue tag="tpos" value="0"/><UML:TaggedValue tag="ea_localid" value="12"/><UML:TaggedValue tag="ea_eleType" value="package"/><UML:TaggedValue tag="style" value="BackColor=-1;BorderColor=-1;BorderWidth=-1;FontColor=-1;VSwimLanes=1;HSwimLanes=1;BorderStyle=0;"/></UML:ModelElement.taggedValue></UML:ClassifierRole></UML:Namespace.ownedElement><UML:Collaboration.interaction/></UML:Collaboration><UML:Comment name="Text" xmi.id="EAID_ED607246_28E4_46b1_97C3_B305573954B9" visibility="public" namespace="EAPK_375FD0CA_EC14_4748_A11E_500A8765E17C"><UML:ModelElement.taggedValue><UML:TaggedValue tag="documentation" value="Rule Views"/><UML:TaggedValue tag="isSpecification" value="false"/><UML:TaggedValue tag="ea_stype" value="Text"/><UML:TaggedValue tag="ea_ntype" value="0"/><UML:TaggedValue tag="version" value="2.0"/><UML:TaggedValue tag="isActive" value="false"/><UML:TaggedValue tag="package" value="EAPK_375FD0CA_EC14_4748_A11E_500A8765E17C"/><UML:TaggedValue tag="date_created" value="2010-06-23 11:54:14"/><UML:TaggedValue tag="date_modified" value="2012-03-14 21:51:05"/><UML:TaggedValue tag="gentype" value="&lt;none&gt;"/><UML:TaggedValue tag="tagged" value="0"/><UML:TaggedValue tag="package_name" value="Rules"/><UML:TaggedValue tag="phase" value="1.0"/><UML:TaggedValue tag="author" value="Johan Wretö"/><UML:TaggedValue tag="complexity" value="1"/><UML:TaggedValue tag="status" value="Implemented"/><UML:TaggedValue tag="tpos" value="0"/><UML:TaggedValue tag="ea_localid" value="56"/><UML:TaggedValue tag="ea_eleType" value="element"/><UML:TaggedValue tag="style" value="BackColor=-1;BorderColor=-1;BorderWidth=-1;FontColor=8388608;VSwimLanes=1;HSwimLanes=1;BorderStyle=0;"/></UML:ModelElement.taggedValue></UML:Comment><UML:Dependency client="EAPK_375FD0CA_EC14_4748_A11E_500A8765E17C" supplier="EAPK_9EFFDA75_39E2_4009_8D22_3FCC20E5E52B" name="initiate, control" xmi.id="EAID_929EAE68_8526_424e_92A7_E520FE2CD659" visibility="public"><UML:ModelElement.taggedValue><UML:TaggedValue tag="style" value="3"/><UML:TaggedValue tag="ea_type" value="Dependency"/><UML:TaggedValue tag="direction" value="Source -&gt; Destination"/><UML:TaggedValue tag="linemode" value="3"/><UML:TaggedValue tag="linecolor" value="-1"/><UML:TaggedValue tag="linewidth" value="0"/><UML:TaggedValue tag="seqno" value="0"/><UML:TaggedValue tag="headStyle" value="0"/><UML:TaggedValue tag="lineStyle" value="0"/><UML:TaggedValue tag="ea_localid" value="67"/><UML:TaggedValue tag="ea_sourceName" value="Rules"/><UML:TaggedValue tag="ea_targetName" value="Process"/><UML:TaggedValue tag="ea_sourceType" value="Package"/><UML:TaggedValue tag="ea_targetType" value="Package"/><UML:TaggedValue tag="ea_sourceID" value="3"/><UML:TaggedValue tag="ea_targetID" value="4"/><UML:TaggedValue tag="src_visibility" value="Public"/><UML:TaggedValue tag="src_aggregation" value="0"/><UML:TaggedValue tag="src_isOrdered" value="false"/><UML:TaggedValue tag="src_targetScope" value="instance"/><UML:TaggedValue tag="src_changeable" value="none"/><UML:TaggedValue tag="src_isNavigable" value="false"/><UML:TaggedValue tag="src_containment" value="Unspecified"/><UML:TaggedValue tag="src_style" value="Union=0;Derived=0;AllowDuplicates=0;Owned=0;Navigable=Non-Navigable;"/><UML:TaggedValue tag="dst_visibility" value="Public"/><UML:TaggedValue tag="dst_aggregation" value="0"/><UML:TaggedValue tag="dst_isOrdered" value="false"/><UML:TaggedValue tag="dst_targetScope" value="instance"/><UML:TaggedValue tag="dst_changeable" value="none"/><UML:TaggedValue tag="dst_isNavigable" value="true"/><UML:TaggedValue tag="dst_containment" value="Unspecified"/><UML:TaggedValue tag="dst_style" value="Union=0;Derived=0;AllowDuplicates=0;Owned=0;Navigable=Navigable;"/><UML:TaggedValue tag="virtualInheritance" value="0"/><UML:TaggedValue tag="mt" value="initiate, control"/></UML:ModelElement.taggedValue></UML:Dependency><UML:Dependency client="EAPK_375FD0CA_EC14_4748_A11E_500A8765E17C" supplier="EAPK_6D1FB119_D85D_4098_B124_4CA15DF677D0" name="restrict possible states and state transitions" xmi.id="EAID_A0FE8D7B_EA0F_4128_8B76_B5649DC2513E" visibility="public"><UML:ModelElement.taggedValue><UML:TaggedValue tag="style" value="3"/><UML:TaggedValue tag="ea_type" value="Dependency"/><UML:TaggedValue tag="direction" value="Source -&gt; Destination"/><UML:TaggedValue tag="linemode" value="3"/><UML:TaggedValue tag="linecolor" value="-1"/><UML:TaggedValue tag="linewidth" value="0"/><UML:TaggedValue tag="seqno" value="0"/><UML:TaggedValue tag="headStyle" value="0"/><UML:TaggedValue tag="lineStyle" value="0"/><UML:TaggedValue tag="ea_localid" value="68"/><UML:TaggedValue tag="ea_sourceName" value="Rules"/><UML:TaggedValue tag="ea_targetName" value="Resource"/><UML:TaggedValue tag="ea_sourceType" value="Package"/><UML:TaggedValue tag="ea_targetType" value="Package"/><UML:TaggedValue tag="ea_sourceID" value="3"/><UML:TaggedValue tag="ea_targetID" value="5"/><UML:TaggedValue tag="src_visibility" value="Public"/><UML:TaggedValue tag="src_aggregation" value="0"/><UML:TaggedValue tag="src_isOrdered" value="false"/><UML:TaggedValue tag="src_targetScope" value="instance"/><UML:TaggedValue tag="src_changeable" value="none"/><UML:TaggedValue tag="src_isNavigable" value="false"/><UML:TaggedValue tag="src_containment" value="Unspecified"/><UML:TaggedValue tag="src_style" value="Union=0;Derived=0;AllowDuplicates=0;Owned=0;Navigable=Non-Navigable;"/><UML:TaggedValue tag="dst_visibility" value="Public"/><UML:TaggedValue tag="dst_aggregation" value="0"/><UML:TaggedValue tag="dst_isOrdered" value="false"/><UML:TaggedValue tag="dst_targetScope" value="instance"/><UML:TaggedValue tag="dst_changeable" value="none"/><UML:TaggedValue tag="dst_isNavigable" value="true"/><UML:TaggedValue tag="dst_containment" value="Unspecified"/><UML:TaggedValue tag="dst_style" value="Union=0;Derived=0;AllowDuplicates=0;Owned=0;Navigable=Navigable;"/><UML:TaggedValue tag="virtualInheritance" value="0"/><UML:TaggedValue tag="mt" value="restrict possible states and state transitions"/></UML:ModelElement.taggedValue></UML:Dependency><UML:Dependency client="EAPK_39223B91_5BEA_47fe_887B_A9E2AA19A444" supplier="EAPK_375FD0CA_EC14_4748_A11E_500A8765E17C" name="can be specified by" xmi.id="EAID_A326B3BC_567D_423b_A075_351021D4002F" visibility="public"><UML:ModelElement.taggedValue><UML:TaggedValue tag="style" value="3"/><UML:TaggedValue tag="ea_type" value="Dependency"/><UML:TaggedValue tag="direction" value="Source -&gt; Destination"/><UML:TaggedValue tag="linemode" value="3"/><UML:TaggedValue tag="linecolor" value="-1"/><UML:TaggedValue tag="linewidth" value="0"/><UML:TaggedValue tag="seqno" value="0"/><UML:TaggedValue tag="headStyle" value="0"/><UML:TaggedValue tag="lineStyle" value="0"/><UML:TaggedValue tag="ea_localid" value="69"/><UML:TaggedValue tag="ea_sourceName" value="Goal"/><UML:TaggedValue tag="ea_targetName" value="Rules"/><UML:TaggedValue tag="ea_sourceType" value="Package"/><UML:TaggedValue tag="ea_targetType" value="Package"/><UML:TaggedValue tag="ea_sourceID" value="6"/><UML:TaggedValue tag="ea_targetID" value="3"/><UML:TaggedValue tag="src_visibility" value="Public"/><UML:TaggedValue tag="src_aggregation" value="0"/><UML:TaggedValue tag="src_isOrdered" value="false"/><UML:TaggedValue tag="src_targetScope" value="instance"/><UML:TaggedValue tag="src_changeable" value="none"/><UML:TaggedValue tag="src_isNavigable" value="false"/><UML:TaggedValue tag="src_containment" value="Unspecified"/><UML:TaggedValue tag="src_style" value="Union=0;Derived=0;AllowDuplicates=0;Owned=0;Navigable=Non-Navigable;"/><UML:TaggedValue tag="dst_visibility" value="Public"/><UML:TaggedValue tag="dst_aggregation" value="0"/><UML:TaggedValue tag="dst_isOrdered" value="false"/><UML:TaggedValue tag="dst_targetScope" value="instance"/><UML:TaggedValue tag="dst_changeable" value="none"/><UML:TaggedValue tag="dst_isNavigable" value="true"/><UML:TaggedValue tag="dst_containment" value="Unspecified"/><UML:TaggedValue tag="dst_style" value="Union=0;Derived=0;AllowDuplicates=0;Owned=0;Navigable=Navigable;"/><UML:TaggedValue tag="virtualInheritance" value="0"/><UML:TaggedValue tag="mt" value="can be specified by"/></UML:ModelElement.taggedValue></UML:Dependency><UML:Package name="Business rules" xmi.id="EAPK_0DB4257C_0307_491f_8099_460B82488F86" isRoot="false" isLeaf="false" isAbstract="false" visibility="public"><UML:ModelElement.taggedValue><UML:TaggedValue tag="parent" value="EAPK_375FD0CA_EC14_4748_A11E_500A8765E17C"/><UML:TaggedValue tag="created" value="2009-04-16 00:00:00"/><UML:TaggedValue tag="modified" value="2012-03-14 21:51:05"/><UML:TaggedValue tag="iscontrolled" value="TRUE"/><UML:TaggedValue tag="xmlpath" value="ea4\460B82488F86.xml"/><UML:TaggedValue tag="lastloaddate" value="2014-02-24 20:40:17"/><UML:TaggedValue tag="lastsavedate" value="2014-02-24 20:40:17"/><UML:TaggedValue tag="version" value="2.0"/><UML:TaggedValue tag="isprotected" value="FALSE"/><UML:TaggedValue tag="usedtd" value="FALSE"/><UML:TaggedValue tag="logxml" value="FALSE"/><UML:TaggedValue tag="batchsave" value="0"/><UML:TaggedValue tag="batchload" value="0"/><UML:TaggedValue tag="packageFlags" value="VCCFG=cosaq-sandbox;"/><UML:TaggedValue tag="savedasstub" value="true"/><UML:TaggedValue tag="phase" value="1.0"/><UML:TaggedValue tag="status" value="Implemented"/><UML:TaggedValue tag="author" value="Johan Wretö"/><UML:TaggedValue tag="complexity" value="1"/><UML:TaggedValue tag="ea_stype" value="Public"/></UML:ModelElement.taggedValue></UML:Package></UML:Namespace.ownedElement></UML:Package></UML:Namespace.ownedElement></UML:Model><UML:Diagram name="Rules" xmi.id="EAID_DA508CCC_6859_4a2c_937F_9B5BD72DBBE8" diagramType="PackageDiagram" owner="EAPK_375FD0CA_EC14_4748_A11E_500A8765E17C" toolName="Enterprise Architect 2.5"><UML:ModelElement.taggedValue><UML:TaggedValue tag="version" value="2.0"/><UML:TaggedValue tag="author" value="Johan Wretö"/><UML:TaggedValue tag="created_date" value="2014-02-24 20:40:17"/><UML:TaggedValue tag="modified_date" value="2014-02-24 20:40:17"/><UML:TaggedValue tag="package" value="EAPK_375FD0CA_EC14_4748_A11E_500A8765E17C"/><UML:TaggedValue tag="type" value="Package"/><UML:TaggedValue tag="swimlanes" value="locked=false;orientation=0;width=0;inbar=false;names=false;color=0;bold=false;fcol=0;;cls=0;"/><UML:TaggedValue tag="matrixitems" value="locked=false;matrixactive=false;swimlanesactive=true;width=1;"/><UML:TaggedValue tag="ea_localid" value="10"/><UML:TaggedValue tag="EAStyle" value="ShowPrivate=1;ShowProtected=1;ShowPublic=1;HideRelationships=0;Locked=0;Border=1;HighlightForeign=1;PackageContents=1;SequenceNotes=0;ScalePrintImage=0;PPgs.cx=1;PPgs.cy=1;DocSize.cx=827;DocSize.cy=1169;ShowDetails=0;Orientation=P;Zoom=100;ShowTags=0;OpParams=1;VisibleAttributeDetail=0;ShowOpRetType=1;ShowIcons=1;CollabNums=0;HideProps=0;ShowReqs=0;ShowCons=0;PaperSize=9;HideParents=0;UseAlias=0;HideAtts=0;HideOps=0;HideStereo=0;HideElemStereo=0;ShowTests=0;ShowMaint=0;ConnectorNotation=UML 2.1;ExplicitNavigability=0;AdvancedElementProps=1;AdvancedFeatureProps=1;AdvancedConnectorProps=1;ShowNotes=0;SuppressBrackets=0;SuppConnectorLabels=0;PrintPageHeadFoot=0;ShowAsList=0;"/><UML:TaggedValue tag="styleex" value="SaveTag=C4894D39;ExcludeRTF=0;DocAll=0;HideQuals=0;AttPkg=1;ShowTests=0;ShowMaint=0;SuppressFOC=1;MatrixActive=0;SwimlanesActive=1;MatrixLineWidth=1;MatrixLocked=0;TConnectorNotation=UML 2.1;TExplicitNavigability=0;AdvancedElementProps=1;AdvancedFeatureProps=1;AdvancedConnectorProps=1;ProfileData=;MDGDgm=;STBLDgm=;ShowNotes=0;VisibleAttributeDetail=0;ShowOpRetType=1;SuppressBrackets=0;SuppConnectorLabels=0;PrintPageHeadFoot=0;ShowAsList=0;SuppressedCompartments=;"/></UML:ModelElement.taggedValue><UML:Diagram.element><UML:DiagramElement geometry="Left=62;Top=43;Right=456;Bottom=79;" subject="EAID_03033933_69CD_487d_9F51_8B10753069F4" seqno="1" style="DUID=95A09FBB;"/><UML:DiagramElement geometry="Left=62;Top=21;Right=152;Bottom=44;" subject="EAID_ED607246_28E4_46b1_97C3_B305573954B9" seqno="2" style="font=Arial;bold=1;italic=0;ul=0;charset=0;pitch=34;fontsz=120;DUID=F5FD247D;"/><UML:DiagramElement geometry="Left=62;Top=117;Right=243;Bottom=170;" subject="EAID_0DB4257C_0307_491f_8099_460B82488F86" seqno="3" style="NSL=0;BCol=-1;BFol=-1;LCol=-1;LWth=-1;fontsz=0;bold=0;italic=0;ul=0;charset=0;pitch=0;DUID=2103D510;"/></UML:Diagram.element></UML:Diagram><UML:DiagramElement geometry="Left=396;Top=430;Right=526;Bottom=510;" subject="EAID_375FD0CA_EC14_4748_A11E_500A8765E17C" seqno="2" style="NSL=0;BFol=-1;LCol=-1;LWth=-1;fontsz=0;bold=0;italic=0;ul=0;charset=0;pitch=0;BCol=14804223;DUID=F9B6E08A;"><UML:ModelElement.taggedValue><UML:TaggedValue tag="diagram_guid" value="EAID_975AA842_F988_4425_AEA5_7576A31F896A"/></UML:ModelElement.taggedValue></UML:DiagramElement><UML:DiagramElement geometry="SX=0;SY=0;EX=0;EY=0;EDGE=1;$LLB=;LLT=;LMT=CX=39:CY=26:OX=21:OY=2:HDN=0:BLD=0:ITA=0:UND=0:CLR=-1:ALN=0:DIR=0:ROT=0;LMB=;LRT=;LRB=;IRHS=;ILHS=;" subject="EAID_929EAE68_8526_424e_92A7_E520FE2CD659" style="Mode=3;EOID=03F929CE;SOID=0D36B0A4;Color=-1;LWidth=0;"><UML:ModelElement.taggedValue><UML:TaggedValue tag="diagram_guid" value="EAID_975AA842_F988_4425_AEA5_7576A31F896A"/><UML:TaggedValue tag="hidden" value="0"/></UML:ModelElement.taggedValue></UML:DiagramElement><UML:DiagramElement geometry="SX=0;SY=0;EX=0;EY=0;EDGE=4;$LLB=;LLT=;LMT=CX=75:CY=39:OX=69:OY=-5:HDN=0:BLD=0:ITA=0:UND=0:CLR=-1:ALN=1:DIR=0:ROT=0;LMB=;LRT=;LRB=;IRHS=;ILHS=;" subject="EAID_A0FE8D7B_EA0F_4128_8B76_B5649DC2513E" style="Mode=3;EOID=35D5538F;SOID=0D36B0A4;Color=-1;LWidth=0;"><UML:ModelElement.taggedValue><UML:TaggedValue tag="diagram_guid" value="EAID_975AA842_F988_4425_AEA5_7576A31F896A"/><UML:TaggedValue tag="hidden" value="0"/></UML:ModelElement.taggedValue></UML:DiagramElement><UML:DiagramElement geometry="SX=0;SY=0;EX=0;EY=0;EDGE=2;$LLB=;LLT=;LMT=CX=45:CY=39:OX=27:OY=-64:HDN=0:BLD=0:ITA=0:UND=0:CLR=-1:ALN=1:DIR=0:ROT=0;LMB=;LRT=;LRB=;IRHS=;ILHS=;" subject="EAID_A326B3BC_567D_423b_A075_351021D4002F" style="Mode=3;EOID=0D36B0A4;SOID=71BE080F;Color=-1;LWidth=0;"><UML:ModelElement.taggedValue><UML:TaggedValue tag="diagram_guid" value="EAID_975AA842_F988_4425_AEA5_7576A31F896A"/><UML:TaggedValue tag="hidden" value="0"/><UML:TaggedValue tag="path" value="461:-148;"/></UML:ModelElement.taggedValue></UML:DiagramElement></XMI.content><XMI.difference/><XMI.extensions xmi.extender="Enterprise Architect 2.5"><EAStub xmi.id="EAPK_9EFFDA75_39E2_4009_8D22_3FCC20E5E52B" name="Process" UMLType="Package"/><EAStub xmi.id="EAPK_6D1FB119_D85D_4098_B124_4CA15DF677D0" name="Resource" UMLType="Package"/><EAStub xmi.id="EAPK_39223B91_5BEA_47fe_887B_A9E2AA19A444" name="Goal" UMLType="Package"/></XMI.extensions></XMI>
